.long-description.html
README.txt
setup.py
docs/CREDITS.txt
docs/HISTORY.txt
docs/INSTALL.txt
src/collective/__init__.py
src/collective.pfg.payment.egg-info/PKG-INFO
src/collective.pfg.payment.egg-info/SOURCES.txt
src/collective.pfg.payment.egg-info/dependency_links.txt
src/collective.pfg.payment.egg-info/entry_points.txt
src/collective.pfg.payment.egg-info/namespace_packages.txt
src/collective.pfg.payment.egg-info/not-zip-safe
src/collective.pfg.payment.egg-info/requires.txt
src/collective.pfg.payment.egg-info/top_level.txt
src/collective/pfg/__init__.py
src/collective/pfg/payment/__init__.py
src/collective/pfg/payment/configure.zcml
src/collective/pfg/payment/error.py
src/collective/pfg/payment/upgrades.py
src/collective/pfg/payment/upgrades.zcml
src/collective/pfg/payment/Extensions/Install.py
src/collective/pfg/payment/Extensions/__init__.py
src/collective/pfg/payment/adapter/__init__.py
src/collective/pfg/payment/adapter/configure.zcml
src/collective/pfg/payment/adapter/properties.py
src/collective/pfg/payment/browser/__init__.py
src/collective/pfg/payment/browser/configure.zcml
src/collective/pfg/payment/browser/miscellaneous.py
src/collective/pfg/payment/browser/payment_interface.py
src/collective/pfg/payment/browser/template.py
src/collective/pfg/payment/browser/viewlet.py
src/collective/pfg/payment/browser/templates/edit_order_number.pt
src/collective/pfg/payment/browser/templates/payment_config.pt
src/collective/pfg/payment/browser/templates/payment_succeeded.pt
src/collective/pfg/payment/browser/viewlets/local_payment.pt
src/collective/pfg/payment/browser/viewlets/payment_properties.pt
src/collective/pfg/payment/content/__init__.py
src/collective/pfg/payment/content/number.py
src/collective/pfg/payment/interfaces/__init__.py
src/collective/pfg/payment/interfaces/adapter.py
src/collective/pfg/payment/interfaces/content.py
src/collective/pfg/payment/interfaces/marker.py
src/collective/pfg/payment/interfaces/utility.py
src/collective/pfg/payment/interfaces/viewlet_manager.py
src/collective/pfg/payment/locales/collective.pfg.payment.pot
src/collective/pfg/payment/locales/fi/LC_MESSAGES/collective.pfg.payment.po
src/collective/pfg/payment/profiles/default/actions.xml
src/collective/pfg/payment/profiles/default/controlpanel.xml
src/collective/pfg/payment/profiles/default/metadata.xml
src/collective/pfg/payment/profiles/default/propertiestool.xml
