Metadata-Version: 1.1
Name: collective.pfg.payment
Version: 0.6
Summary: Extends PloneFormGen to payment form.
Home-page: https://github.com/taito/collective.pfg.payment
Author: Taito Horiuchi
Author-email: taito.horiuchi@gmail.com
License: BSD
Platform: UNKNOWN
Classifier: Framework :: Plone
Classifier: Framework :: Plone :: 4.3
Classifier: License :: OSI Approved :: BSD License
Classifier: Programming Language :: Python
Classifier: Programming Language :: Python :: 2.7
